pam_tester/__init__.py
pam_tester/pam_tester.py
pam_tester-0.0.3.dist-info/METADATA
pam_tester-0.0.3.dist-info/WHEEL
pam_tester-0.0.3.dist-info/entry_points.txt
pam_tester-0.0.3.dist-info/RECORD
