Metadata-Version: 2.1
Name: pam-tester
Version: 0.0.3
Summary: Tool for testing PAM configurations
Home-page: https://github.com/dev-sec/pam-tester
License: GPL-3.0-only
Author: Martin Schurz
Author-email: Martin.Schurz@telekom.de
Requires-Python: >=3.6,<4.0
Classifier: License :: OSI Approved :: GNU General Public License v3 (GPLv3)
Classifier: Programming Language :: Python :: 3
Classifier: Programming Language :: Python :: 3.6
Classifier: Programming Language :: Python :: 3.7
Classifier: Programming Language :: Python :: 3.8
Classifier: Programming Language :: Python :: 3.9
Classifier: Programming Language :: Python :: 3.10
Classifier: Programming Language :: Python :: 3.11
Requires-Dist: click (>=8.0.4,<9.0.0)
Requires-Dist: pam (>=0.2.0,<0.3.0)
Requires-Dist: six (>=1.16.0,<2.0.0)
Project-URL: Changelog, https://github.com/dev-sec/pam-tester/blob/master/CHANGELOG.md
Project-URL: Documentation, https://github.com/dev-sec/pam-tester
Project-URL: Repository, https://github.com/dev-sec/pam-tester
